py_babelnet/__init__.py
py_babelnet/calls.py
py_babelnet-0.0.2.dist-info/LICENSE
py_babelnet-0.0.2.dist-info/METADATA
py_babelnet-0.0.2.dist-info/WHEEL
py_babelnet-0.0.2.dist-info/top_level.txt
py_babelnet-0.0.2.dist-info/RECORD
