Metadata-Version: 2.1
Name: py-babelnet
Version: 0.0.2
Summary: Python package for babelnet API
Home-page: UNKNOWN
Author: Pablo Torres
Author-email: pablo.torres.t@gmail.com
License: MIT
Platform: UNKNOWN
Classifier: Programming Language :: Python :: 3.6
Requires-Dist: requests
